celery_streaming_result/__init__.py
celery_streaming_result/core.py
celery_streaming_result-0.1.3.dist-info/LICENSE
celery_streaming_result-0.1.3.dist-info/METADATA
celery_streaming_result-0.1.3.dist-info/WHEEL
celery_streaming_result-0.1.3.dist-info/top_level.txt
celery_streaming_result-0.1.3.dist-info/RECORD
