Metadata-Version: 2.1
Name: celery-streaming-result
Version: 0.1.3
Summary: Celery任务结果分片管理
Author: Zhou WeiKe
Maintainer: Zhou WeiKe
License: MIT
Keywords: celery_streaming_result,celery,streaming result
Classifier: Development Status :: 5 - Production/Stable
Classifier: Intended Audience :: Developers
Classifier: Topic :: Software Development :: Libraries :: Python Modules
Classifier: License :: OSI Approved :: MIT License
Classifier: Programming Language :: Python :: 3
Classifier: Programming Language :: Python :: 3 :: Only
License-File: LICENSE
Requires-Dist: msgpack
Requires-Dist: celery
Requires-Dist: redis
Requires-Dist: asgiref
